strawberry_django_pubsub/__init__.py
strawberry_django_pubsub/context.py
strawberry_django_pubsub/event.py
strawberry_django_pubsub/queue.py
strawberry_django_pubsub/serializer.py
strawberry_django_pubsub/types.py
strawberry_django_pubsub-0.0.10a0.dist-info/LICENSE
strawberry_django_pubsub-0.0.10a0.dist-info/WHEEL
strawberry_django_pubsub-0.0.10a0.dist-info/METADATA
strawberry_django_pubsub-0.0.10a0.dist-info/RECORD
